aminoae/__init__.py
aminoae/acm.py
aminoae/client.py
aminoae/client2.py
aminoae/socket.py
aminoae/sub_client.py
aminoae/asyncfix/__init__.py
aminoae/asyncfix/acm.py
aminoae/asyncfix/client.py
aminoae/asyncfix/socket.py
aminoae/asyncfix/sub_client.py
aminoae/lib/__init__.py
aminoae/lib/exceptions.py
aminoae/lib/headers.py
aminoae/lib/helpers.py
aminoae/lib/objects.py
aminoae/lib/util/__init__.py
aminoae/lib/util/exceptions.py
aminoae/lib/util/headers.py
aminoae/lib/util/helpers.py
aminoae/lib/util/objects.py
amino.ae-3.0.0.1.dist-info/METADATA
amino.ae-3.0.0.1.dist-info/WHEEL
amino.ae-3.0.0.1.dist-info/top_level.txt
amino.ae-3.0.0.1.dist-info/RECORD
