Metadata-Version: 2.1
Name: amino.ae
Version: 3.0.0.1
Summary: Library for Amino by Anime Empire. Discord - https://discord.gg/NnKWCtY2F8
Home-page: https://github.com/BlackReaper33/amino.ae
Author: Reaper
Author-email: animeempire10@gmail.com
License: MIT
Keywords: aminoapps,amino.ae,amino,amino-bot,narvii,api,python,python3,python3.x,reaper
Requires-Python: >=3.6
Requires-Dist: requests
Requires-Dist: websocket-client ==1.3.1
Requires-Dist: setuptools
Requires-Dist: json-minify
Requires-Dist: six
Requires-Dist: aiohttp
Requires-Dist: websockets
